macaquedb/Database.py
macaquedb/__init__.py
macaquedb/database/Image.py
macaquedb/database/Session.py
macaquedb/database/Subject.py
macaquedb/database/__init__.py
macaquedb/database/utilities.py
macaquedb-1.0.5.dist-info/METADATA
macaquedb-1.0.5.dist-info/WHEEL
macaquedb-1.0.5.dist-info/top_level.txt
macaquedb-1.0.5.dist-info/RECORD
